{"result":[{"idx":"1439","reg_date":"2023-07-03 00:02:42","timestamp":"1688310162","uuid":"64a19192bb4cd","rand_str":"4ljNaZ","now_time":"00:02:42"},{"idx":"1438","reg_date":"2023-07-03 00:01:40","timestamp":"1688310100","uuid":"64a19154ba897","rand_str":"XgJ3QH","now_time":"00:01:40"},{"idx":"1437","reg_date":"2023-07-03 00:00:38","timestamp":"1688310038","uuid":"64a19116ba4d5","rand_str":"NE3M7v","now_time":"00:00:38"},{"idx":"1436","reg_date":"2023-07-02 23:59:37","timestamp":"1688309977","uuid":"64a190d968a65","rand_str":"s8JR3r","now_time":"23:59:37"},{"idx":"1435","reg_date":"2023-07-02 23:58:36","timestamp":"1688309916","uuid":"64a1909c253a7","rand_str":"gUvL44","now_time":"23:58:36"},{"idx":"1434","reg_date":"2023-07-02 23:57:34","timestamp":"1688309854","uuid":"64a1905ee3641","rand_str":"xIPvW8","now_time":"23:57:34"},{"idx":"1433","reg_date":"2023-07-02 23:56:33","timestamp":"1688309793","uuid":"64a190218af97","rand_str":"LrpFkl","now_time":"23:56:33"},{"idx":"1432","reg_date":"2023-07-02 23:55:32","timestamp":"1688309732","uuid":"64a18fe452283","rand_str":"xbDFVq","now_time":"23:55:32"},{"idx":"1431","reg_date":"2023-07-02 23:54:31","timestamp":"1688309671","uuid":"64a18fa723214","rand_str":"OAySyc","now_time":"23:54:31"},{"idx":"1430","reg_date":"2023-07-02 23:53:29","timestamp":"1688309609","uuid":"64a18f69cff8e","rand_str":"l3YouB","now_time":"23:53:29"},{"idx":"1429","reg_date":"2023-07-02 23:52:28","timestamp":"1688309548","uuid":"64a18f2c9dd41","rand_str":"RuF4Kr","now_time":"23:52:28"},{"idx":"1428","reg_date":"2023-07-02 23:51:27","timestamp":"1688309487","uuid":"64a18eef6a971","rand_str":"A4n0eK","now_time":"23:51:27"},{"idx":"1427","reg_date":"2023-07-02 23:50:26","timestamp":"1688309426","uuid":"64a18eb25632b","rand_str":"s4IKGC","now_time":"23:50:26"},{"idx":"1426","reg_date":"2023-07-02 23:49:25","timestamp":"1688309365","uuid":"64a18e7524fef","rand_str":"YmxJhK","now_time":"23:49:25"},{"idx":"1425","reg_date":"2023-07-02 23:48:23","timestamp":"1688309303","uuid":"64a18e37e2492","rand_str":"WAy2JT","now_time":"23:48:23"},{"idx":"1424","reg_date":"2023-07-02 23:47:22","timestamp":"1688309242","uuid":"64a18dfaab7c4","rand_str":"N6C3GR","now_time":"23:47:22"},{"idx":"1423","reg_date":"2023-07-02 23:46:21","timestamp":"1688309181","uuid":"64a18dbd762d6","rand_str":"ygYN0v","now_time":"23:46:21"},{"idx":"1422","reg_date":"2023-07-02 23:45:20","timestamp":"1688309120","uuid":"64a18d8010654","rand_str":"yU3yLO","now_time":"23:45:20"},{"idx":"1421","reg_date":"2023-07-02 23:44:19","timestamp":"1688309059","uuid":"64a18d43129d6","rand_str":"a8IzhA","now_time":"23:44:19"},{"idx":"1420","reg_date":"2023-07-02 23:43:17","timestamp":"1688308997","uuid":"64a18d0534dc4","rand_str":"Xw1aoF","now_time":"23:43:17"},{"idx":"1419","reg_date":"2023-07-02 23:42:15","timestamp":"1688308935","uuid":"64a18cc71af32","rand_str":"EsAOB4","now_time":"23:42:15"},{"idx":"1418","reg_date":"2023-07-02 23:41:13","timestamp":"1688308873","uuid":"64a18c895a72a","rand_str":"AiiWv2","now_time":"23:41:13"},{"idx":"1417","reg_date":"2023-07-02 23:40:11","timestamp":"1688308811","uuid":"64a18c4b7e70f","rand_str":"mfW5vJ","now_time":"23:40:11"},{"idx":"1416","reg_date":"2023-07-02 23:39:09","timestamp":"1688308749","uuid":"64a18c0df2795","rand_str":"Buv1Vh","now_time":"23:39:09"},{"idx":"1415","reg_date":"2023-07-02 23:38:08","timestamp":"1688308688","uuid":"64a18bd0901e6","rand_str":"1jmxhw","now_time":"23:38:08"},{"idx":"1414","reg_date":"2023-07-02 23:37:07","timestamp":"1688308627","uuid":"64a18b9334fa0","rand_str":"aSPSuC","now_time":"23:37:07"},{"idx":"1413","reg_date":"2023-07-02 23:36:05","timestamp":"1688308565","uuid":"64a18b55ee263","rand_str":"Qtbbyu","now_time":"23:36:05"},{"idx":"1412","reg_date":"2023-07-02 23:35:04","timestamp":"1688308504","uuid":"64a18b18d5d38","rand_str":"BYXlbX","now_time":"23:35:04"},{"idx":"1411","reg_date":"2023-07-02 23:34:03","timestamp":"1688308443","uuid":"64a18adb72515","rand_str":"uQ1F5n","now_time":"23:34:03"},{"idx":"1410","reg_date":"2023-07-02 23:33:01","timestamp":"1688308381","uuid":"64a18a9d597ab","rand_str":"w6NrYx","now_time":"23:33:01"},{"idx":"1409","reg_date":"2023-07-02 23:31:57","timestamp":"1688308317","uuid":"64a18a5dd2d7f","rand_str":"CsJ7GS","now_time":"23:31:57"},{"idx":"1408","reg_date":"2023-07-02 23:30:54","timestamp":"1688308254","uuid":"64a18a1e89d1e","rand_str":"hGlaA2","now_time":"23:30:54"},{"idx":"1407","reg_date":"2023-07-02 23:29:52","timestamp":"1688308192","uuid":"64a189e0a069d","rand_str":"4DfqAJ","now_time":"23:29:52"},{"idx":"1406","reg_date":"2023-07-02 23:28:50","timestamp":"1688308130","uuid":"64a189a269c6e","rand_str":"oZ0PdC","now_time":"23:28:50"},{"idx":"1405","reg_date":"2023-07-02 23:27:48","timestamp":"1688308068","uuid":"64a189649437a","rand_str":"jXpNC4","now_time":"23:27:48"},{"idx":"1404","reg_date":"2023-07-02 23:26:46","timestamp":"1688308006","uuid":"64a189267adbe","rand_str":"J7RtD2","now_time":"23:26:46"},{"idx":"1403","reg_date":"2023-07-02 23:25:42","timestamp":"1688307942","uuid":"64a188e6b74d2","rand_str":"2rXB4c","now_time":"23:25:42"},{"idx":"1402","reg_date":"2023-07-02 23:24:40","timestamp":"1688307880","uuid":"64a188a8717dd","rand_str":"fDbapn","now_time":"23:24:40"},{"idx":"1401","reg_date":"2023-07-02 23:23:39","timestamp":"1688307819","uuid":"64a1886b1e989","rand_str":"7QG2Fs","now_time":"23:23:39"},{"idx":"1400","reg_date":"2023-07-02 23:22:38","timestamp":"1688307758","uuid":"64a1882e08b16","rand_str":"AvNMxo","now_time":"23:22:38"},{"idx":"1399","reg_date":"2023-07-02 23:21:36","timestamp":"1688307696","uuid":"64a187f0e946c","rand_str":"UTM9gv","now_time":"23:21:36"},{"idx":"1398","reg_date":"2023-07-02 23:20:35","timestamp":"1688307635","uuid":"64a187b3b326d","rand_str":"eZGPpj","now_time":"23:20:35"},{"idx":"1397","reg_date":"2023-07-02 23:19:34","timestamp":"1688307574","uuid":"64a1877695a6c","rand_str":"u3iGIB","now_time":"23:19:34"},{"idx":"1396","reg_date":"2023-07-02 23:18:33","timestamp":"1688307513","uuid":"64a187399caa4","rand_str":"cvPdrs","now_time":"23:18:33"},{"idx":"1395","reg_date":"2023-07-02 23:18:16","timestamp":"1688307496","uuid":"64a1872824a09","rand_str":"CJVUv1","now_time":"23:18:16"},{"idx":"1394","reg_date":"2023-07-02 23:17:15","timestamp":"1688307435","uuid":"64a186eb9cdd0","rand_str":"1n4rk0","now_time":"23:17:15"},{"idx":"1393","reg_date":"2023-07-02 23:16:14","timestamp":"1688307374","uuid":"64a186ae99974","rand_str":"pVLUJL","now_time":"23:16:14"},{"idx":"1392","reg_date":"2023-07-02 23:15:14","timestamp":"1688307314","uuid":"64a186723e0ad","rand_str":"Rj8zbH","now_time":"23:15:14"},{"idx":"1391","reg_date":"2023-07-02 23:14:12","timestamp":"1688307252","uuid":"64a18634a6d92","rand_str":"wpSuvn","now_time":"23:14:12"},{"idx":"1390","reg_date":"2023-07-02 23:13:10","timestamp":"1688307190","uuid":"64a185f6c0638","rand_str":"Fhi21Y","now_time":"23:13:10"},{"idx":"1389","reg_date":"2023-07-02 23:11:56","timestamp":"1688307116","uuid":"64a185ac9f0b8","rand_str":"X9VE8k","now_time":"23:11:56"},{"idx":"1388","reg_date":"2023-07-02 23:10:49","timestamp":"1688307049","uuid":"64a1856922d81","rand_str":"DYHi6H","now_time":"23:10:49"},{"idx":"1387","reg_date":"2023-07-02 23:09:48","timestamp":"1688306988","uuid":"64a1852c416e1","rand_str":"dWAJ4F","now_time":"23:09:48"},{"idx":"1386","reg_date":"2023-07-02 23:08:47","timestamp":"1688306927","uuid":"64a184efaae68","rand_str":"H2GpCn","now_time":"23:08:47"},{"idx":"1385","reg_date":"2023-07-02 23:07:47","timestamp":"1688306867","uuid":"64a184b328ba3","rand_str":"9Hkdu9","now_time":"23:07:47"},{"idx":"1384","reg_date":"2023-07-02 23:06:46","timestamp":"1688306806","uuid":"64a18476b4fcb","rand_str":"mieHDf","now_time":"23:06:46"},{"idx":"1383","reg_date":"2023-07-02 23:05:46","timestamp":"1688306746","uuid":"64a1843a4b3a5","rand_str":"MLtJKb","now_time":"23:05:46"},{"idx":"1382","reg_date":"2023-07-02 23:04:45","timestamp":"1688306685","uuid":"64a183fd35f53","rand_str":"wpUUlQ","now_time":"23:04:45"},{"idx":"1381","reg_date":"2023-07-02 23:03:44","timestamp":"1688306624","uuid":"64a183c0a09f3","rand_str":"Ai3K0v","now_time":"23:03:44"},{"idx":"1380","reg_date":"2023-07-02 23:02:43","timestamp":"1688306563","uuid":"64a18383809f2","rand_str":"ol3EVz","now_time":"23:02:43"},{"idx":"1379","reg_date":"2023-07-02 23:01:38","timestamp":"1688306498","uuid":"64a18342e08a5","rand_str":"bm7f5O","now_time":"23:01:38"},{"idx":"1378","reg_date":"2023-07-02 23:00:31","timestamp":"1688306431","uuid":"64a182ffd323d","rand_str":"C3NFRC","now_time":"23:00:31"},{"idx":"1377","reg_date":"2023-07-02 22:59:28","timestamp":"1688306368","uuid":"64a182c04c6fa","rand_str":"wW8sny","now_time":"22:59:28"},{"idx":"1376","reg_date":"2023-07-02 22:58:27","timestamp":"1688306307","uuid":"64a1828327180","rand_str":"6u6UYG","now_time":"22:58:27"},{"idx":"1375","reg_date":"2023-07-02 22:57:10","timestamp":"1688306230","uuid":"64a182369b7bc","rand_str":"GckMhM","now_time":"22:57:10"},{"idx":"1374","reg_date":"2023-07-02 22:55:57","timestamp":"1688306157","uuid":"64a181ed06dfb","rand_str":"hZz05D","now_time":"22:55:57"},{"idx":"1373","reg_date":"2023-07-02 22:54:55","timestamp":"1688306095","uuid":"64a181af91361","rand_str":"QPrl33","now_time":"22:54:55"},{"idx":"1372","reg_date":"2023-07-02 22:53:55","timestamp":"1688306035","uuid":"64a18173114db","rand_str":"4ZzzZJ","now_time":"22:53:55"},{"idx":"1371","reg_date":"2023-07-02 22:52:54","timestamp":"1688305974","uuid":"64a181368df88","rand_str":"j54cd0","now_time":"22:52:54"},{"idx":"1370","reg_date":"2023-07-02 22:51:54","timestamp":"1688305914","uuid":"64a180fa073fe","rand_str":"4SyTuq","now_time":"22:51:54"},{"idx":"1369","reg_date":"2023-07-02 22:50:53","timestamp":"1688305853","uuid":"64a180bd7d365","rand_str":"Bm338J","now_time":"22:50:53"},{"idx":"1368","reg_date":"2023-07-02 22:49:52","timestamp":"1688305792","uuid":"64a18080cc9f3","rand_str":"1vpAkQ","now_time":"22:49:52"},{"idx":"1367","reg_date":"2023-07-02 22:48:52","timestamp":"1688305732","uuid":"64a180446826a","rand_str":"c4EqBe","now_time":"22:48:52"},{"idx":"1366","reg_date":"2023-07-02 22:47:51","timestamp":"1688305671","uuid":"64a18007dd12a","rand_str":"mumaat","now_time":"22:47:51"},{"idx":"1365","reg_date":"2023-07-02 22:46:50","timestamp":"1688305610","uuid":"64a17fca680fc","rand_str":"gUsnPY","now_time":"22:46:50"},{"idx":"1364","reg_date":"2023-07-02 22:45:49","timestamp":"1688305549","uuid":"64a17f8da27ec","rand_str":"uJkQ75","now_time":"22:45:49"},{"idx":"1363","reg_date":"2023-07-02 22:44:45","timestamp":"1688305485","uuid":"64a17f4d8e3aa","rand_str":"S7UxNu","now_time":"22:44:45"},{"idx":"1362","reg_date":"2023-07-02 22:43:44","timestamp":"1688305424","uuid":"64a17f10e8b4b","rand_str":"AbGIsm","now_time":"22:43:44"},{"idx":"1361","reg_date":"2023-07-02 22:42:42","timestamp":"1688305362","uuid":"64a17ed25773e","rand_str":"meJdqw","now_time":"22:42:42"},{"idx":"1360","reg_date":"2023-07-02 22:41:40","timestamp":"1688305300","uuid":"64a17e94e66e7","rand_str":"sjS0wE","now_time":"22:41:40"},{"idx":"1359","reg_date":"2023-07-02 22:40:39","timestamp":"1688305239","uuid":"64a17e57d9ab0","rand_str":"Kw4hza","now_time":"22:40:39"},{"idx":"1358","reg_date":"2023-07-02 22:39:38","timestamp":"1688305178","uuid":"64a17e1a159f8","rand_str":"RMwcLi","now_time":"22:39:38"},{"idx":"1357","reg_date":"2023-07-02 22:38:37","timestamp":"1688305117","uuid":"64a17dddb2117","rand_str":"1jiqhl","now_time":"22:38:37"},{"idx":"1356","reg_date":"2023-07-02 22:37:36","timestamp":"1688305056","uuid":"64a17da01e755","rand_str":"VEGUg5","now_time":"22:37:36"},{"idx":"1355","reg_date":"2023-07-02 22:36:35","timestamp":"1688304995","uuid":"64a17d63a8d49","rand_str":"v2wvtI","now_time":"22:36:35"},{"idx":"1354","reg_date":"2023-07-02 22:35:34","timestamp":"1688304934","uuid":"64a17d26b876d","rand_str":"haL2ey","now_time":"22:35:34"},{"idx":"1353","reg_date":"2023-07-02 22:34:33","timestamp":"1688304873","uuid":"64a17ce9a8418","rand_str":"PxwScu","now_time":"22:34:33"},{"idx":"1352","reg_date":"2023-07-02 22:33:31","timestamp":"1688304811","uuid":"64a17cabeac66","rand_str":"KpIO3o","now_time":"22:33:31"},{"idx":"1351","reg_date":"2023-07-02 22:32:30","timestamp":"1688304750","uuid":"64a17c6eb8cc0","rand_str":"BfNyEC","now_time":"22:32:30"},{"idx":"1350","reg_date":"2023-07-02 22:31:29","timestamp":"1688304689","uuid":"64a17c31050f5","rand_str":"cls3Lf","now_time":"22:31:29"},{"idx":"1349","reg_date":"2023-07-02 22:30:27","timestamp":"1688304627","uuid":"64a17bf3a1d2e","rand_str":"KqiWCg","now_time":"22:30:27"},{"idx":"1348","reg_date":"2023-07-02 22:29:26","timestamp":"1688304566","uuid":"64a17bb6be061","rand_str":"8PKj25","now_time":"22:29:26"},{"idx":"1347","reg_date":"2023-07-02 22:28:26","timestamp":"1688304506","uuid":"64a17b7a5a1b3","rand_str":"f0Aj2B","now_time":"22:28:26"},{"idx":"1346","reg_date":"2023-07-02 22:27:25","timestamp":"1688304445","uuid":"64a17b3def313","rand_str":"XlJAyW","now_time":"22:27:25"},{"idx":"1345","reg_date":"2023-07-02 22:26:25","timestamp":"1688304385","uuid":"64a17b01a0e5c","rand_str":"wocKfO","now_time":"22:26:25"},{"idx":"1344","reg_date":"2023-07-02 22:25:25","timestamp":"1688304325","uuid":"64a17ac530365","rand_str":"CfeFU0","now_time":"22:25:25"},{"idx":"1343","reg_date":"2023-07-02 22:24:24","timestamp":"1688304264","uuid":"64a17a8893050","rand_str":"FH4J8f","now_time":"22:24:24"},{"idx":"1342","reg_date":"2023-07-02 22:23:24","timestamp":"1688304204","uuid":"64a17a4c2e122","rand_str":"c03Nwi","now_time":"22:23:24"},{"idx":"1341","reg_date":"2023-07-02 22:22:23","timestamp":"1688304143","uuid":"64a17a0fbee3c","rand_str":"E6tSoM","now_time":"22:22:23"},{"idx":"1340","reg_date":"2023-07-02 22:21:23","timestamp":"1688304083","uuid":"64a179d350bf3","rand_str":"Jk4LOv","now_time":"22:21:23"}]}